Metadata-Version: 1.0
Name: template-extension
Version: 0.7
Summary: template for freecad extensions, installable with pip
Home-page: https://github.com/looooo/TemplateExtension
Author: looooo
Author-email: sppedflyer@gmail.com
License: UNKNOWN
Platform: UNKNOWN
